Metadata-Version: 1.1
Name: django-filechooser
Version: 0.1.1
Summary: jQuery Filechooser for Django projects
Home-page: https://github.com/martinvw/django-filechooser
Author: Martin van Wingerden
Author-email: martinvw@gmail.com
License: MIT
Download-URL: https://github.com/martinvw/django-filechooser/archive/v0.1.1.tar.gz
Keywords: django-filechooser
Platform: UNKNOWN
Classifier: Development Status :: 4 - Beta
Classifier: Intended Audience :: Developers
Classifier: Programming Language :: Python :: 3
Classifier: Programming Language :: Python :: 3.2
Classifier: Programming Language :: Python :: 3.3
Classifier: Programming Language :: Python :: 3.4
Classifier: Operating System :: OS Independent
Classifier: Topic :: Software Development :: Libraries
Classifier: Topic :: Utilities
Classifier: Environment :: Web Environment
Classifier: Framework :: Django
